{
	"Agatha Harkness": {
		"manual": {
			"board": [
				{
					"name": "constraints",
					"is_cost": true,
					"tags": [
						"alter_ego_action"
					]
				},
				{
					"name": "exhaust_card",
					"is_cost": true,
					"subject": "self"
				},
				{
					"name": "move_card_to_container",
					"subject": "tutor",
					"sort_descending": true,
					"subject_count": 3,
					"src_container": "deck",
					"dest_container": "deck",
					"dest_index": "bottom"
				},
				{
					"name": "move_card_to_container",
					"subject": "previous",
					"subject_count": "all",
					"dest_container": "hand",
					"selection_count": 1,
					"needs_selection": true
				}
			]
		}
	},
	"Bait and Switch": {
		"manual": {
			"hand": [
				{
					"name": "villain_attacks_you"
				},
				{
					"name": "thwart",
					"amount": 4,
					"subject": "main_scheme"
				}
			]
		}
	},
	"Browbeat": {
		"manual": {
			"hand": [
				{
					"name": "constraints",
					"is_cost": true,
					"tags": [
						"hero_action"
					],
				},
				{
					"name": "attack",
					"amount": 2,
					"plus_amount": {
						"func_name": "get_subject_int_property",
						"func_params": {
							"subject": "villain",
							"property": "stage_int",
							"max": 3
						}
					},
					"subject": "villain"
				}
			]
		}
	},
	"Chaos Magic": {
		"manual": {
			"hand": [
				{
					"name": "constraints",
					"is_cost": true,
					"tags": [
						"hero_action"
					]
				},
				{
					"name": "force_play_card",
					"ignore_resource_cost": true,
					"subject": "tutor",
					"subject_count": "all",
					"needs_subject": true,
					"subject_exclude": "self",
					"src_container": "hand",
					"needs_selection": true,
					"selection_count": 1,
					"selection_optional": true
				},
				{
					"name": "discard",
					"subject": "tutor",
					"sort_descending": true,
					"src_container": "deck_villain",
					"up_to": true,
					"subject_count": {
						"func_name": "get_subject_int_printed_property",
						"func_params": {
							"subject": "previous",
							"property": "cost"
						}
					}
				}
			]
		}
	},
	"Chaos Manipulation": {
		"reveal": {
			"all": [
				{
					"name": "move_card_to_board",
					"destination_grid": "enemies_my_hero",
					"subject": "tutor",
					"src_container": [
						"deck_villain",
						"discard_villain"
					],
					"filter_state_tutor": [
						{
							"filter_properties": {
								"shortname": "Luminous"
							}
						}
					]
				},
				{
					"name": "sequence",
					"sequence_ability": "discard_and_count",
					"subject": "self",
					"count": 2,
					"delay_until_no_activity": true
				},
				{
					"name": "sequence",
					"sequence_ability": "do_attack",
					"subject": "self",
					"delay_until_no_activity": true
				}
			]
		},
		"discard_and_count": {
			"_silent": true,
			"all": [
				{
					"name": "discard",
					"subject": "index",
					"subject_index": "top",
					"src_container": "deck_villain",
					"is_cost": true
				},
				{
					"name": "save_variable",
					"var_name": "my_boost_count",
					"var_type": "int",
					"mode": "add",
					"value": {
						"func_name": "count_boost_icons",
						"func_params": {
							"subject": "previous"
						}
					},
					"_comments": "remembering the card for attack"
				}
			]
		},
		"do_attack": {
			"_silent": true,
			"condition_all": {
				"func_name": "get_subject_int_variable>=2",
				"func_params": {
					"subject": "self",
					"variable": "my_boost_count"
				}
			},
			"all": [
				{
					"name": "enemy_activates",
					"subject": "Luminous"
				}
			]
		}
	},
	"Crisis Averted": {
		"manual": {
			"hand": [
				{
					"name": "constraints",
					"is_cost": true,
					"tags": [
						"hero_action"
					]
				},
				{
					"name": "thwart",
					"amount": 6,
					"subject": "main_scheme",
					"tags": {
						"if": {
							"func_name": "paid_with_includes",
							"func_params": {
								"mental": 1
							}
						},
						"then": [
							"bypass_crisis"
						],
						"else": []
					}
				}
			]
		}
	},
	"Heroic Intuition": {
		"manual": {
			"hand": [
				{
					"name": "constraints",
					"is_cost": true,
					"max_per_hero_any": 1
				}
			]
		},
		"card_moved_to_board": {
			"trigger": "self",
			"board": [
				{
					"name": "move_to_player_zone",
					"subject": "boardseek",
					"subject_count": "all",
					"selection_count": 1,
					"selection_type": "equal",
					"needs_selection": true,
					"filter_state_seek": [
						{
							"filter_group": "group_identities",
							"filter_max_per_hero": 1
						}
					]
				}
			]
		},
		"alterants": {
			"board": [
				{
					"filter_task": "get_property",
					"filter_property_name": "thwart",
					"filter_same_controller": true,
					"filter_state_trigger": [
						{
							"filter_group": "group_identities"
						}
					],
					"alteration": 1
				}
			]
		}
	},
	"Hex Bolt": {
		"manual": {
			"hand": [
				{
					"name": "constraints",
					"is_cost": true,
					"tags": [
						"hero_action"
					]
				},
				{
					"name": "sequence",
					"sequence_ability": "hex_bolt",
					"subject": "self",
					"delay_until_no_activity": true,
					"count": 3
				}
			]
		},
		"hex_bolt": {
			"all": [
				{
					"name": "discard",
					"subject": "index",
					"subject_index": "top",
					"src_container": "deck_villain",
					"is_cost": true
				},
				{
					"name": "conditional_script",
					"condition_number": {
						"func_name": "count_boost_icons",
						"func_params": {
							"subject": "previous"
						}
					},
					"options": [
						{
							"condition": 0,
							"nested_tasks": [
								{
									"name": "deal_damage",
									"amount": 2,
									"subject": "an_enemy"
								}
							]
						},
						{
							"condition": 1,
							"nested_tasks": [
								{
									"name": "remove_threat",
									"amount": 2,
									"subject": "target",
									"needs_subject": true,
									"filter_state_subject": [
										{
											"filter_group": "group_schemes"
										}
									]
								}
							]
						},
						{
							"condition": 2,
							"nested_tasks": [
								{
									"name": "draw_cards",
									"amount": 1
								}
							]
						}
					],
					"else": [
						{
							"name": "sequence",
							"sequence_ability": "status",
							"subject": "self"
						}
					]
				}
			]
		},
		"status": {
			"all": {
				"Tough": [
					{
						"name": "mod_tokens",
						"token_name": "tough",
						"modification": 1,
						"subject": "target",
						"filter_state_subject": [
							{
								"filter_group": "group_characters"
							}
						]
					}
				],
				"Stunned": [
					{
						"name": "mod_tokens",
						"token_name": "stunned",
						"modification": 1,
						"subject": "target",
						"filter_state_subject": [
							{
								"filter_group": "group_characters"
							}
						]
					}
				],
				"Confused": [
					{
						"name": "mod_tokens",
						"token_name": "confused",
						"modification": 1,
						"subject": "target",
						"filter_state_subject": [
							{
								"filter_group": "group_characters"
							}
						]
					}
				]
			}
		}
	},
	"Last Stand": {
		"interrupt_attack_started": {
			"filter_state_trigger": [
				{
					"filter_same_controller": true,
					"filter_properties": {
						"type_code": "ally"
					}
				}
			],
			"is_optional_hand": true,
			"hand": [
				{
					"name": "constraints",
					"is_cost": true,
					"tags": [
						"hero_interrupt"
					]
				},
				{
					"name": "save_variable",
					"var_name": "my_ally",
					"var_type": "subject",
					"value": "trigger",
					"_comments": "remembering the card for alterant use"
				},
				{
					"name": "add_script",
					"subject": "self",
					"end_condition": "attack_happened",
					"script": {
						"alterants": {
							"all": [
								{
									"filter_task": "get_property",
									"filter_property_name": "attack",
									"trigger": "my_ally",
									"alteration": 3
								}
							]
						},
						"interrupt_attack_happened": {
							"all": [
								{
									"name": "discard",
									"subject": "my_ally"
								}
							]
						}
					}
				}
			]
		}
	},
	"Luminous": {
		"response": {
			"event_name": [
				"enemy_scheme_happened",
				"enemy_attack_happened"
			],
			"trigger": "self",
			"board": [
				{
					"name": "discard",
					"subject": "index",
					"subject_index": "top",
					"src_container": "deck_villain",
					"is_cost": true
				},
				{
					"name": "deal_encounter",
					"subject": "current_activation_target",
					"amount": {
						"func_name": "count_boost_icons>=2",
						"func_params": {
							"subject": "previous"
						}
					}
				}
			]
		}
	},
	"Magic Shield": {
		"interrupt": {
			"event_name": "receive_damage",
			"event_filters": {
				"filter_state_event_target": [
					{
						"filter_group": "group_friendly"
					}
				]
			},
			"is_optional_board": true,
			"board": [
				{
					"name": "discard",
					"subject": "self"
				},
				{
					"name": "prevent",
					"amount": 3,
					"subject": "interrupted_event"
				}
			]
		}
	},
	"Magical Suspension": {
		"card_moved_to_board": {
			"trigger": "self",
			"board": [
				{
					"name": "attach_to_card",
					"subject": "my_identity"
				}
			]
		},
		"alterants": {
			"board": [
				{
					"filter_task": "get_property",
					"filter_property_name": "cost",
					"filter_state_trigger": [
						{
							"filter_same_controller": true
						}
					],
					"alteration": 1
				}
			]
		},
		"manual": {
			"board": [
				{
					"name": "constraints",
					"is_cost": true,
					"tags": [
						"hero_action"
					]
				},
				{
					"name": "exhaust_card",
					"is_cost": true,
					"subject": "host"
				},
				{
					"name": "discard",
					"subject": "self"
				}
			]
		}
	},
	"Molecular Decay": {
		"manual": {
			"hand": [
				{
					"name": "constraints",
					"is_cost": true,
					"tags": [
						"hero_action"
					]
				},
				{
					"name": "nop",
					"subject": "an_enemy",
					"needs_subject": true,
					"tags": [
						"attack"
					]
				},
				{
					"name": "save_variable",
					"var_name": "my_enemy",
					"var_type": "subject",
					"value": "previous"
				},
				{
					"name": "sequence",
					"sequence_ability": "discard_and_count",
					"subject": "self",
					"count": 2,
					"delay_until_no_activity": true
				},
				{
					"name": "sequence",
					"sequence_ability": "do_damage",
					"subject": "self",
					"delay_until_no_activity": true
				}
			]
		},
		"discard_and_count": {
			"_silent": true,
			"all": [
				{
					"name": "discard",
					"subject": "index",
					"subject_index": "top",
					"src_container": "deck_villain",
					"is_cost": true
				},
				{
					"name": "save_variable",
					"var_name": "my_boost_count",
					"var_type": "int",
					"mode": "add",
					"value": {
						"func_name": "count_boost_icons",
						"func_params": {
							"subject": "previous"
						}
					},
					"_comments": "remembering the card for damage"
				}
			]
		},
		"do_damage": {
			"_silent": true,
			"all": [
				{
					"name": "attack",
					"amount": 5,
					"plus_amount": "my_boost_count",
					"subject": "my_enemy"
				}
			]
		}
	},
	"Multitasking": {
		"manual": {
			"hand": [
				{
					"name": "constraints",
					"is_cost": true,
					"tags": [
						"hero_action"
					]
				},
				{
					"name": "thwart",
					"amount": 2,
					"subject": "target",
					"needs_subject": true,
					"filter_state_subject": [
						{
							"filter_group": "group_schemes"
						}
					]
				},
				{
					"name": "thwart",
					"amount": {
						"if": {
							"func_name": "paid_with_includes",
							"func_params": {
								"mental": 1
							}
						},
						"then": 2,
						"else": 0
					},
					"exclude_subject": "previous",
					"subject": "target",
					"needs_subject": true,
					"filter_state_subject": [
						{
							"filter_group": "group_schemes"
						}
					]
				}
			]
		}
	},
	"Order and Chaos": {
		"interrupt": {
			"event_name": "reveal_encounter",
			"filter_state_trigger": [
				{
					"filter_properties": {
						"type_code": "treachery"
					}
				}
			],
			"is_optional_hand": true,
			"hand": [
				{
					"name": "constraints",
					"is_cost": true,
					"tags": [
						"hero_interrupt"
					],
					"team_up": [
						"Quicksilver",
						"Scarlet Witch"
					]
				},
				{
					"name": "prevent",
					"subject": "interrupted_event"
				},
				{
					"name": "deal_damage",
					"amount": 2,
					"subject": "villain"
				}
			]
		}
	},
	"Quicksilver - Pietro Maximoff": {
		"once_per_phase": {
			"__name__": "__ready"
		},
		"manual": {
			"board": [
				{
					"name": "constraints",
					"is_cost": true,
					"tags": [
						"action_ability"
					]
				},
				{
					"name": "mod_tokens",
					"is_cost": true,
					"token_name": "__ready",
					"modification": -1,
					"subject": "self"
				},
				{
					"name": "ready_card",
					"subject": "self"
				}
			]
		}
	},
	"Recuperation": {
		"manual": {
			"hand": [
				{
					"name": "constraints",
					"is_cost": true,
					"tags": [
						"alter_ego_action"
					]
				},
				{
					"name": "heal",
					"subject": "my_identity",
					"amount": {
						"func_name": "get_subject_int_property",
						"func_params": {
							"subject": "my_identity",
							"property": "recover"
						}
					}
				}
			]
		}
	},
	"Scarlet Witch": {
		"once_per_phase": {
			"__name__": "__chaos_control"
		},
		"interrupt": {
			"trigger": "another",
			"event_definition_contains": "count_boost_icons",
			"is_optional_board": true,
			"condition_board": {
				"func_name": "count_tokens",
				"func_params": {
					"token_name": "__chaos_control"
				}
			},
			"board": {
				"_rules": {
					"choice_msg_suffix": [
						"(current boost icons:",
						{
							"func_name": "precompute_value",
							"func_params": {
								"subject": "interrupted_event",
								"func_find_in_definition": "count_boost_icons"
							}
						},
						")"
					]
				},
				"Discard another boost": [
					{
						"name": "constraints",
						"is_cost": true,
						"tags": [
							"hero_interrupt"
						]
					},
					{
						"name": "mod_tokens",
						"token_name": "__chaos_control",
						"modification": -1,
						"is_cost": true,
						"subject": "self"
					},
					{
						"name": "discard",
						"subject": "index",
						"subject_index": "top",
						"src_container": "deck_villain",
						"is_cost": true
					},
					{
						"name": "replacement_effect",
						"subject": "interrupted_event",
						"replacements": {
							"replace": {
								"find_in_definition": "count_boost_icons",
								"modify_path": "../..",
								"alteration": {
									"func_name": "count_boost_icons",
									"func_params": {
										"subject": "previous"
									}
								}
							}
						}
					}
				],
				"Skip": [
					{
						"name": "nop"
					}
				]
			}
		},
		"interrupt_boost_card_resolved": {
			"is_optional_board": "true",
			"condition_board": {
				"func_name": "count_tokens",
				"func_params": {
					"token_name": "__chaos_control"
				}
			},
			"board": {
				"_rules": {
					"choice_msg_suffix": [
						"(current boost icons:",
						"trigger_details_boost_icons",
						")"
					]
				},
				"Discard another boost": [
					{
						"name": "constraints",
						"is_cost": true,
						"tags": [
							"hero_interrupt"
						]
					},
					{
						"name": "mod_tokens",
						"token_name": "__chaos_control",
						"modification": -1,
						"is_cost": true,
						"subject": "self"
					},
					{
						"name": "discard",
						"subject": "index",
						"subject_index": "top",
						"src_container": "deck_villain",
						"is_cost": true
					},
					{
						"name": "increase",
						"subject": "current_activation",
						"amount": {
							"func_name": "count_boost_icons",
							"func_params": {
								"subject": "previous"
							}
						}
					},
					{
						"name": "prevent",
						"subject": "current_activation",
						"amount": "trigger_details_boost_icons"
					}
				],
				"Skip": [
					{
						"name": "nop"
					}
				]
			}
		}
	},
	"Scarlet Witch's Crest": {
		"interrupt": {
			"trigger": "another",
			"event_definition_contains": "count_boost_icons",
			"is_optional_board": true,
			"condition_board": {
				"func_name": "is_ready"
			},
			"board": {
				"_rules": {
					"choice_msg_suffix": [
						"(current boost icons:",
						{
							"func_name": "precompute_value",
							"func_params": {
								"subject": "interrupted_event",
								"func_find_in_definition": "count_boost_icons"
							}
						},
						")"
					]
				},
				"+1": [
					{
						"name": "exhaust_card",
						"subject": "self",
						"is_cost": true
					},
					{
						"name": "replacement_effect",
						"subject": "interrupted_event",
						"replacements": {
							"plus": {
								"find_in_definition": "count_boost_icons",
								"modify_path": "../../func_params/plus",
								"alteration": 1
							}
						}
					}
				],
				"Skip": [
					{
						"name": "nop"
					}
				],
				"-1": [
					{
						"name": "exhaust_card",
						"subject": "self",
						"is_cost": true
					},
					{
						"name": "replacement_effect",
						"subject": "interrupted_event",
						"replacements": {
							"plus": {
								"find_in_definition": "count_boost_icons",
								"modify_path": "../../func_params/plus",
								"alteration": -1
							}
						}
					}
				]
			}
		},
		"interrupt_boost_card_resolved": {
			"is_optional_board": true,
			"condition_board": {
				"func_name": "is_ready"
			},
			"board": {
				"_rules": {
					"choice_msg_suffix": [
						"(current boost icons:",
						"trigger_details_boost_icons",
						")"
					]
				},
				"+1": [
					{
						"name": "exhaust_card",
						"subject": "self",
						"is_cost": true
					},
					{
						"name": "add_boost",
						"amount": 1,
						"subject": "trigger",
						"force_valid_boost_target": true
					}
				],
				"Skip": [
					{
						"name": "nop"
					}
				],
				"-1": [
					{
						"name": "exhaust_card",
						"subject": "self",
						"is_cost": true
					},
					{
						"name": "add_boost",
						"amount": -1,
						"subject": "trigger",
						"force_valid_boost_target": true
					}
				]
			}
		}
	},
	"Slipping Sanity": {
		"give_obligation": {
			"__to__": "Wanda Maximoff"
		},
		"card_moved_to_board": {
			"trigger": "self",
			"board": {
				"_rules": {
					"forced": true
				},
				"Flip then remove from the game": {
					"obligation_flip_remove": {}
				},
				"Remove from the game": {
					"obligation_remove": {}
				},
				"Flip then Discard & Threat": [
					{
						"name": "constraints",
						"is_cost": true,
						"tags": [
							"hero_form"
						]
					},
					{
						"name": "exhaust_card",
						"is_cost": true,
						"subject": "my_identity"
					},
					{
						"name": "change_form",
						"subject": "my_hero"
					},
					{
						"name": "discard",
						"subject": "tutor",
						"src_container": "deck_villain",
						"subject_count": 5,
						"up_to": true,
						"sort_descending": true,
						"is_cost": true
					},
					{
						"name": "add_threat",
						"subject": "main_scheme",
						"amount": {
							"func_name": "get_subject_int_printed_property",
							"func_params": {
								"subject": "previous",
								"property": "boost_star"
							}
						}
					},
					{
						"name": "discard",
						"subject": "self"
					}
				],
				"Discard & Threat": [
					{
						"name": "discard",
						"subject": "tutor",
						"src_container": "deck_villain",
						"subject_count": 5,
						"up_to": true,
						"sort_descending": true,
						"is_cost": true
					},
					{
						"name": "add_threat",
						"subject": "main_scheme",
						"amount": {
							"func_name": "get_subject_int_printed_property",
							"func_params": {
								"subject": "previous",
								"property": "boost_star"
							}
						}
					},
					{
						"name": "discard",
						"subject": "self"
					}
				]
			}
		}
	},
	"Speed - Thomas Shepherd": {
		"once_per_round": {
			"__name__": "__speed"
		},
		"thwart_happened": {
			"trigger": "self",
			"is_optional_board": true,
			"board": [
				{
					"name": "mod_tokens",
					"token_name": "__speed",
					"modification": -1,
					"is_cost": true,
					"subject": "self"
				},
				{
					"name": "ready_card",
					"subject": "self"
				}
			]
		}
	},
	"Spiritual Meditation": {
		"manual": {
			"hand": [
				{
					"name": "constraints",
					"is_cost": true,
					"tags": [
						"action_ability"
					]
				},
				{
					"name": "draw_cards",
					"amount": 2,
					"is_cost": true
				},
				{
					"name": "sequence",
					"sequence_ability": "do_discard"
				}
			]
		},
		"do_discard": {
			"all": [
				{
					"name": "discard",
					"subject": "tutor",
					"src_container": "hand",
					"subject_count": "all",
					"needs_selection": true,
					"selection_count": 1,
					"selection_optional": false,
					"selection_type": "equal"
				}
			]
		}
	},
	"Swift Retribution": {
		"manual": {
			"hand": [
				{
					"name": "constraints",
					"is_cost": true,
					"tags": [
						"hero_action"
					]
				},
				{
					"name": "enemy_schemes",
					"subject": "villain"
				},
				{
					"name": "sequence",
					"sequence_ability": "post_scheme_attack",
					"subject": "self",
					"delay_until_no_activity": true
				}
			]
		},
		"post_scheme_attack": {
			"all": [
				{
					"name": "attack",
					"amount": 4,
					"subject": "villain"
				}
			]
		}
	},
	"The Next Evolution": {
		"alterants": {
			"board": [
				{
					"filter_task": "get_property",
					"filter_property_name": "boost",
					"filter_state_trigger": [
						{
							"filter_func": {
								"func_name": "is_encounter"
							}
						}
					],
					"alteration": 1
				}
			]
		}
	},
	"The Power of Justice": {
		"resource": {
			"hand": [
				{
					"name": "nop",
					"fail_cost_on_skip": true,
					"is_cost": true,
					"filter_state_trigger": [
						{
							"filter_properties": {
								"faction_code": "justice"
							}
						}
					]
				},
				{
					"name": "add_resource",
					"amount": 2,
					"resource_name": "wild"
				}
			]
		}
	},
	"Turn the Tide": {
		"response_last_threat_removed": {
			"event_filters": {
				"source": "my_hero",
				"tags": [
					"thwart"
				]
			},
			"is_optional_hand": true,
			"hand": [
				{
					"name": "attack",
					"amount": 3,
					"subject": "an_enemy"
				}
			]
		}
	},
	"Wanda Maximoff": {
		"once_per_round": {
			"__name__": "__superpowered_siblings"
		},
		"manual": {
			"board": {
				"Superpowered Siblings": [
					{
						"name": "constraints",
						"is_cost": true,
						"tags": [
							"action_ability"
						]
					},
					{
						"name": "mod_tokens",
						"token_name": "__superpowered_siblings",
						"modification": -1,
						"is_cost": true,
						"subject": "self"
					},
					{
						"name": "discard",
						"subject": "tutor",
						"src_container": "hand",
						"subject_count": "all",
						"needs_selection": true,
						"selection_count": 2,
						"selection_type": "equal",
						"is_cost": true
					},
					{
						"name": "draw_cards",
						"amount": {
							"if": {
								"func_name": "card_is_in_play",
								"func_params": {
									"card_name": "Pietro Maximoff"
								}
							},
							"then": 3,
							"else": 2
						}
					}
				]
			}
		}
	},
	"Warp Reality": {
		"interrupt": {
			"event_name": "about_to_reveal",
			"is_optional_hand": true,
			"hand": [
				{
					"name": "cancel_current_encounter"
				},
				{
					"name": "discard",
					"subject": "tutor",
					"sort_descending": true,
					"src_container": "deck_villain",
					"up_to": true,
					"subject_count": {
						"func_name": "get_subject_int_printed_property",
						"func_params": {
							"subject": "trigger",
							"property": "boost"
						}
					}
				}
			]
		}
	},
	"Wiccan - William Kaplan": {
		"thwart_happened": {
			"trigger": "self",
			"is_optional_board": true,
			"board": [
				{
					"name": "discard",
					"subject": "index",
					"subject_index": "top",
					"src_container": "deck_villain",
					"is_cost": true
				},
				{
					"name": "save_variable",
					"var_name": "my_boost_count",
					"var_type": "int",
					"mode": "add",
					"value": {
						"func_name": "count_boost_icons",
						"func_params": {
							"subject": "previous"
						}
					},
					"_comments": "remembering the card for attack"
				},
				{
					"name": "sequence",
					"sequence_ability": "do_damage",
					"subject": "self",
					"delay_until_no_activity": true
				}
			]
		},
		"do_damage": {
			"all": [
				{
					"name": "deal_damage",
					"amount": 1,
					"subject": "boardseek",
					"subject_count": "all",
					"selection_count": "my_boost_count",
					"selection_type": "as_much_as_possible",
					"selection_what_to_count": "assign_any_damage",
					"needs_selection": true,
					"filter_state_seek": [
						{
							"filter_group": "group_enemies"
						}
					]
				}
			]
		}
	}
}