{
	"id": 11401,
	"name": "(Starter) Gamora",
	"date_creation": "2021-07-19T16:41:11+00:00",
	"date_update": "2024-08-17T18:08:28+00:00",
	"description_md": "Starter deck included with the game",
	"user_id": 10394,
	"hero_code": "18001a",
	"hero_name": "Gamora",
	"slots": {
		"01054": 2,
		"01057": 2,
		"01088": 1,
		"01089": 1,
		"01090": 1,
		"18002": 1,
		"18003": 2,
		"18004": 2,
		"18005": 2,
		"18006": 2,
		"18007": 2,
		"18008": 1,
		"18009": 2,
		"18010": 1,
		"18011": 1,
		"18012": 3,
		"18013": 3,
		"18015": 3,
		"18016": 3,
		"18018": 1,
		"18019": 1,
		"18020": 3
	},
	"ignoreDeckLimitSlots": null,
	"version": "1.0",
	"meta": "{\"aspect\":\"aggression\"}",
	"tags": ""
}