{
	"id": 21000,
	"name": "Spider-Ham precon",
	"date_creation": "2022-07-17T22:15:49+00:00",
	"date_update": "2025-11-05T00:20:23+00:00",
	"description_md": "Just the precon deck",
	"user_id": 10671,
	"hero_code": "30001a",
	"hero_name": "Spider-Ham",
	"slots": {
		"30002": 1,
		"30003": 2,
		"30004": 1,
		"30005": 1,
		"30006": 2,
		"30007": 3,
		"30008": 1,
		"30009": 2,
		"30010": 1,
		"30011": 1,
		"30012": 1,
		"30013": 1,
		"30014": 3,
		"30015": 2,
		"30016": 3,
		"30017": 3,
		"30018": 3,
		"30019": 3,
		"30020": 1,
		"30021": 1,
		"30022": 3,
		"30023": 1
	},
	"ignoreDeckLimitSlots": null,
	"version": "1.0",
	"meta": "{\"aspect\":\"justice\"}",
	"tags": ""
}